README.md
setup.py
librelay/__init__.py
librelay/attachment.py
librelay/crypto.py
librelay/errors.py
librelay/eventing.py
librelay/exchange.py
librelay/executor.py
librelay/message_receiver.py
librelay/message_sender.py
librelay/outgoing_message.py
librelay/provisioning_cipher.py
librelay/queue_async.py
librelay/util.py
librelay/websocket_resource.py
librelay.egg-info/PKG-INFO
librelay.egg-info/SOURCES.txt
librelay.egg-info/dependency_links.txt
librelay.egg-info/requires.txt
librelay.egg-info/top_level.txt
librelay/hub/__init__.py
librelay/hub/atlas.py
librelay/hub/http.py
librelay/hub/registration.py
librelay/hub/signal.py
librelay/protobufs/DeviceMessages_pb2.py
librelay/protobufs/IncomingPushMessageSignal_pb2.py
librelay/protobufs/SubProtocol_pb2.py
librelay/protobufs/__init__.py
librelay/storage/__init__.py
librelay/storage/backing/__init__.py
librelay/storage/backing/fs.py
librelay/storage/backing/interface.py