Metadata-Version: 2.1
Name: librelay
Version: 0.10.0
Summary: Forsta messaging protocol library
Home-page: https://github.com/ForstaLabs/librelay-python
Author: Forsta, Inc.
Author-email: support@forsta.io
License: GPL
Platform: UNKNOWN
Classifier: Development Status :: 4 - Beta
Classifier: Intended Audience :: Developers
Classifier: License :: OSI Approved :: GNU General Public License v3 (GPLv3)
Classifier: Operating System :: OS Independent
Classifier: Programming Language :: Python
Classifier: Programming Language :: Python :: 3.6
Classifier: Topic :: Security :: Cryptography
Classifier: Topic :: Software Development :: Libraries
